<annotation>
	<folder>train</folder>
	<filename>gold_mv5.jpg</filename>
	<path>/home/gus/Documents/git/search-rescue_victims_dataset/images/train/gold_mv5.jpg</path>
	<source>
		<database>Unknown</database>
	</source>
	<size>
		<width>720</width>
		<height>720</height>
		<depth>3</depth>
	</size>
	<segmented>0</segmented>
	<object>
		<name>victim</name>
		<pose>Unspecified</pose>
		<truncated>0</truncated>
		<difficult>0</difficult>
		<bndbox>
			<xmin>290</xmin>
			<ymin>214</ymin>
			<xmax>521</xmax>
			<ymax>501</ymax>
		</bndbox>
	</object>
</annotation>
